FacebookAdsWindsorApi/__init__.py
FacebookAdsWindsorApi/client.py
FacebookAdsWindsorApi/enums.py
test/__init__.py
test/tests.py
FacebookAdsWindsorApi-1.0.6.dist-info/METADATA
FacebookAdsWindsorApi-1.0.6.dist-info/WHEEL
FacebookAdsWindsorApi-1.0.6.dist-info/top_level.txt
FacebookAdsWindsorApi-1.0.6.dist-info/RECORD
