Metadata-Version: 2.1
Name: FacebookAdsWindsorApi
Version: 1.0.6
Summary: Easy access to windsor.ai Facebook APIs
Home-page: https://github.com/windsor-ai/FacebookAdsWindsorApi
Author: Windsor AI
Author-email: dev@windsor.ai
Requires-Dist: requests (~=2.25.1)
